ldai/__init__.py
ldai/chat/__init__.py
ldai/client.py
ldai/judge/__init__.py
ldai/judge/evaluation_schema_builder.py
ldai/models.py
ldai/providers/__init__.py
ldai/providers/ai_provider.py
ldai/providers/ai_provider_factory.py
ldai/providers/types.py
ldai/tracker.py
launchdarkly_server_sdk_ai-0.11.0.dist-info/METADATA
launchdarkly_server_sdk_ai-0.11.0.dist-info/WHEEL
launchdarkly_server_sdk_ai-0.11.0.dist-info/RECORD
